<annotation>
	<folder>img_train</folder>
	<filename>507.jpg</filename>
	<path>/tensorflow/BaiduImageSpider-master/img_train/507.jpg</path>
	<source>
		<database>Unknown</database>
	</source>
	<size>
		<width>351</width>
		<height>624</height>
		<depth>3</depth>
	</size>
	<segmented>0</segmented>
	<object>
		<name>book</name>
		<pose>Unspecified</pose>
		<truncated>1</truncated>
		<difficult>0</difficult>
		<bndbox>
			<xmin>8</xmin>
			<ymin>162</ymin>
			<xmax>351</xmax>
			<ymax>584</ymax>
		</bndbox>
	</object>
</annotation>
